measurekit/__init__.py
measurekit/constants.py
measurekit/pandas_ext.py
measurekit/application/__init__.py
measurekit/application/context.py
measurekit/application/factories.py
measurekit/application/parsing.py
measurekit/application/solver_service.py
measurekit/application/startup.py
measurekit/application/functions/__init__.py
measurekit/application/functions/functions.py
measurekit/domain/__init__.py
measurekit/domain/exceptions.py
measurekit/domain/measurement/__init__.py
measurekit/domain/measurement/conversions.py
measurekit/domain/measurement/converters.py
measurekit/domain/measurement/dimensions.py
measurekit/domain/measurement/quantity.py
measurekit/domain/measurement/system.py
measurekit/domain/measurement/uncertainty.py
measurekit/domain/measurement/units.py
measurekit/domain/measurement/vectorized_uncertainty.py
measurekit/domain/measurement/ports/__init__.py
measurekit/domain/measurement/ports/unit_repository.py
measurekit/domain/notation/__init__.py
measurekit/domain/notation/base_entity.py
measurekit/domain/notation/lexer.py
measurekit/domain/notation/parsers.py
measurekit/domain/notation/protocols.py
measurekit/domain/notation/token_buffer.py
measurekit/domain/notation/typing.py
measurekit/domain/symbolic/__init__.py
measurekit/domain/symbolic/expression.py
measurekit/domain/symbolic/quantity.py
measurekit/ext/__init__.py
measurekit/ext/pandas_support.py
measurekit/infrastructure/__init__.py
measurekit/infrastructure/config/measurekit.conf
measurekit/infrastructure/config/systems/imperial.conf
measurekit/infrastructure/config/systems/international.conf
measurekit-0.0.3.dev0.dist-info/licenses/LICENSE
measurekit-0.0.3.dev0.dist-info/METADATA
measurekit-0.0.3.dev0.dist-info/WHEEL
measurekit-0.0.3.dev0.dist-info/top_level.txt
measurekit-0.0.3.dev0.dist-info/RECORD
