Metadata-Version: 2.4
Name: measurekit
Version: 0.0.3.dev0
Summary: A Python package for handling measurement units and conversions
Home-page: https://github.com/irvinrx1996/measurekit
Author: Irvin Torres
Author-email: irvinrx1996@hotmail.com
Project-URL: Bug Reports, https://github.com/irvinrx1996/measurekit/issues
Project-URL: Source, https://github.com/irvinrx1996/measurekit
Project-URL: Documentation, https://measurekit.readthedocs.io/
Keywords: units,measurement,conversion,physics,engineering,science
Classifier: Programming Language :: Python :: 3
Classifier: Programming Language :: Python :: 3.10
Classifier: Programming Language :: Python :: 3.11
Classifier: Programming Language :: Python :: 3.12
Classifier: License :: OSI Approved :: MIT License
Classifier: Operating System :: OS Independent
Classifier: Development Status :: 3 - Alpha
Classifier: Intended Audience :: Developers
Classifier: Intended Audience :: Science/Research
Classifier: Topic :: Scientific/Engineering
Classifier: Topic :: Scientific/Engineering :: Physics
Requires-Python: >=3.10
License-File: LICENSE
Requires-Dist: sympy>=1.4
Requires-Dist: typing-extensions>=4.15.0
Provides-Extra: numpy
Requires-Dist: numpy>=1.21.0; extra == "numpy"
Requires-Dist: scipy>=1.5.0; extra == "numpy"
Provides-Extra: torch
Requires-Dist: torch>=2.0.0; extra == "torch"
Provides-Extra: jax
Requires-Dist: jax>=0.4.0; extra == "jax"
Requires-Dist: jaxlib>=0.4.0; extra == "jax"
Provides-Extra: pandas
Requires-Dist: pandas>=1.3.0; extra == "pandas"
Provides-Extra: all
Requires-Dist: numpy>=1.21.0; extra == "all"
Requires-Dist: scipy>=1.5.0; extra == "all"
Requires-Dist: torch>=2.0.0; extra == "all"
Requires-Dist: jax>=0.4.0; extra == "all"
Requires-Dist: jaxlib>=0.4.0; extra == "all"
Requires-Dist: pandas>=1.3.0; extra == "all"
Provides-Extra: dev
Requires-Dist: pytest>=6.0.0; extra == "dev"
Requires-Dist: pytest-cov>=2.12.0; extra == "dev"
Requires-Dist: black>=21.5b2; extra == "dev"
Requires-Dist: isort>=5.9.1; extra == "dev"
Requires-Dist: mypy>=0.812; extra == "dev"
Requires-Dist: flake8>=3.9.2; extra == "dev"
Requires-Dist: numpy>=1.21.0; extra == "dev"
Requires-Dist: scipy>=1.5.0; extra == "dev"
Provides-Extra: docs
Requires-Dist: sphinx>=4.0.2; extra == "docs"
Requires-Dist: sphinx-rtd-theme>=0.5.2; extra == "docs"
Dynamic: author
Dynamic: author-email
Dynamic: classifier
Dynamic: description
Dynamic: description-content-type
Dynamic: home-page
Dynamic: keywords
Dynamic: license-file
Dynamic: project-url
Dynamic: provides-extra
Dynamic: requires-dist
Dynamic: requires-python
Dynamic: summary
